[
	{
		"title": "Elementor Fullpage Scroll",
		"description": "A Wordpress plugin to build fullpage scrollable sections with Elementor Page Builder.",
		"href": "https://www.rtl-theme.com/pixerul-wordpress-plugin",
		"thumb": "/img/rtl-theme-portfolios/elementor-fullpage-scroll.png",
		"sales": 124,
		"rating": 4.5,
		"reviewsCount": 15
	},
	{
		"title": "Elementor Fullpage Accordion",
		"description": "A Wordpress plugin to build fullpage accordions with Elementor Page Builder.",
		"href": "https://www.rtl-theme.com/elementor-fullpage-accordion-wordpress-plugin",
		"thumb": "/img/rtl-theme-portfolios/elementor-fullpage-accordion.png",
		"sales": 7,
		"rating": null,
		"reviewsCount": 0
	}
]
